cloud_storage_mocker/__init__.py
cloud_storage_mocker/_core.py
cloud_storage_mocker/_version.py
cloud_storage_mocker-0.3.4.dist-info/METADATA
cloud_storage_mocker-0.3.4.dist-info/WHEEL
cloud_storage_mocker-0.3.4.dist-info/licenses/LICENSE
cloud_storage_mocker-0.3.4.dist-info/RECORD
